banana_server/__init__.py
banana_server/banana.py
banana_server-0.0.1.dist-info/LICENSE
banana_server-0.0.1.dist-info/METADATA
banana_server-0.0.1.dist-info/WHEEL
banana_server-0.0.1.dist-info/top_level.txt
banana_server-0.0.1.dist-info/RECORD
