Metadata-Version: 2.1
Name: banana-server
Version: 0.0.1
Summary: The banana package is a python client to interact with your machine learning models hosted on Banana
Home-page: https://www.banana.dev
Author: Erik Dunteman
Author-email: erik@banana.dev
License: Apache License 2.0
Keywords: Banana server,HTTP server,Banana,Framework
Classifier: Development Status :: 3 - Alpha
Classifier: Intended Audience :: Developers
Classifier: Topic :: Software Development :: Build Tools
Classifier: License :: OSI Approved :: MIT License
Classifier: Programming Language :: Python :: 3.7
Classifier: Programming Language :: Python :: 3.8
License-File: LICENSE
Requires-Dist: sanic (<=22.0.0)
